epubsum/__init__.py
epubsum/__main__.py
epubsum/epubsum.py
epubsum-0.3.dist-info/entry_points.txt
epubsum-0.3.dist-info/LICENSE
epubsum-0.3.dist-info/WHEEL
epubsum-0.3.dist-info/METADATA
epubsum-0.3.dist-info/RECORD
