Metadata-Version: 2.1
Name: epubsum
Version: 0.3
Summary: epubsum.
Author-email: Graham Wheeler <graham@grahamwheeler.com>
Classifier: License :: OSI Approved :: MIT License
Classifier: Programming Language :: Python :: 3
Classifier: Topic :: Text Processing :: Linguistic
Requires-Dist: bs4
Requires-Dist: clean-text
Requires-Dist: docopt
Requires-Dist: ebooklib
Requires-Dist: flit_core >=3.7
Requires-Dist: textsum
Project-URL: Source, https://github.com/gramster/epubsum
